Mashup_package/__init__.py
Mashup_package/download.py
mashup_102218038-1.0.0.dist-info/METADATA
mashup_102218038-1.0.0.dist-info/WHEEL
mashup_102218038-1.0.0.dist-info/top_level.txt
mashup_102218038-1.0.0.dist-info/RECORD
