Metadata-Version: 2.1
Name: mashup-102218038
Version: 1.0.0
Summary: Package to make mashups from youtube videos
Author: thebrownkidd
Keywords: python,audio,mashup,youtube
Classifier: Development Status :: 1 - Planning
Classifier: Intended Audience :: Developers
Classifier: Programming Language :: Python :: 3
Classifier: Operating System :: Unix
Classifier: Operating System :: MacOS :: MacOS X
Classifier: Operating System :: Microsoft :: Windows
